pinnacle/__init__.py
pinnacle/sdk.py
pinnacle/hooks/__init__.py
pinnacle/hooks/hook.py
pinnacle/models/__init__.py
pinnacle/models/base.py
pinnacle/models/bet_statuses.py
pinnacle/models/betlist.py
pinnacle/models/bets_get_bets_by_type_v4_bet_type.py
pinnacle/models/betting_status_response.py
pinnacle/models/cancellation_details_item.py
pinnacle/models/cancellation_reason.py
pinnacle/models/get_bets_by_type_response_v4.py
pinnacle/models/manual_bet.py
pinnacle/models/multi_bet_request_special_bet_request.py
pinnacle/models/multi_bet_response_special_bet_response.py
pinnacle/models/odds_format.py
pinnacle/models/parlay_bet.py
pinnacle/models/parlay_leg.py
pinnacle/models/parlay_leg_request.py
pinnacle/models/parlay_leg_response.py
pinnacle/models/place_bet_request.py
pinnacle/models/place_parlay_bet_request.py
pinnacle/models/place_parlay_bet_response.py
pinnacle/models/place_straight_bet_response.py
pinnacle/models/place_teaser_bet_leg_response.py
pinnacle/models/place_teaser_bet_request.py
pinnacle/models/place_teaser_bet_response.py
pinnacle/models/round_robin_option_with_odds.py
pinnacle/models/sort_dir.py
pinnacle/models/special_bet.py
pinnacle/models/special_bet_request.py
pinnacle/models/special_bet_response.py
pinnacle/models/straight_bet_v4.py
pinnacle/models/teaser_bet.py
pinnacle/models/teaser_bet_leg.py
pinnacle/models/teaser_leg.py
pinnacle/models/utils/cast_models.py
pinnacle/models/utils/json_map.py
pinnacle/net/__init__.py
pinnacle/net/environment/__init__.py
pinnacle/net/environment/environment.py
pinnacle/net/headers/__init__.py
pinnacle/net/headers/base_header.py
pinnacle/net/headers/basic_auth.py
pinnacle/net/request_chain/__init__.py
pinnacle/net/request_chain/request_chain.py
pinnacle/net/request_chain/handlers/__init__.py
pinnacle/net/request_chain/handlers/base_handler.py
pinnacle/net/request_chain/handlers/hook_handler.py
pinnacle/net/request_chain/handlers/http_handler.py
pinnacle/net/request_chain/handlers/retry_handler.py
pinnacle_bets_client-1.0.0.dist-info/LICENSE
pinnacle_bets_client-1.0.0.dist-info/METADATA
pinnacle_bets_client-1.0.0.dist-info/WHEEL
pinnacle_bets_client-1.0.0.dist-info/top_level.txt
pinnacle_bets_client-1.0.0.dist-info/RECORD
