Metadata-Version: 2.1
Name: pinnacle-bets-client
Version: 1.0.0
Summary: All about bets, place bets, get your bet history or current bet status.  # Authentication   Please note that API has restriction that client password can be maximum up 10 characters long.   API uses HTTP Basic access authentication. You need to send Authorization HTTP Request header:    `Authorization: Basic <Base64 value of UTF-8 encoded  username:password >`  Example:  `Authorization: Basic U03MyOT23YbzMDc6d3c3O1DQ1` 
License: MIT
Requires-Python: >=3.7
License-File: LICENSE
Requires-Dist: requests >=2.31.0
